gtm_mcp/__init__.py
gtm_mcp/gtm_client.py
gtm_mcp/server.py
gtm_mcp/tools.py
gtm_mcp/utils.py
gtm_mcp/tests/test_gtm_client.py
gtm_mcp-0.2.0.dist-info/METADATA
gtm_mcp-0.2.0.dist-info/WHEEL
gtm_mcp-0.2.0.dist-info/entry_points.txt
gtm_mcp-0.2.0.dist-info/licenses/LICENSE
gtm_mcp-0.2.0.dist-info/RECORD
