Metadata-Version: 2.4
Name: gtm-mcp
Version: 0.2.0
Summary: MCP server for Google Tag Manager
Project-URL: Homepage, https://github.com/paolobtl/gtm-mcp
Project-URL: Repository, https://github.com/paolobtl/gtm-mcp
Project-URL: Issues, https://github.com/paolobtl/gtm-mcp/issues
Author-email: Paolo Bietolini <chat@paolobietolini.com>
License: MIT
License-File: LICENSE
Keywords: claude,google-tag-manager,gtm,mcp
Classifier: Development Status :: 3 - Alpha
Classifier: Intended Audience :: Developers
Classifier: License :: OSI Approved :: MIT License
Classifier: Programming Language :: Python :: 3
Classifier: Programming Language :: Python :: 3.10
Classifier: Programming Language :: Python :: 3.11
Classifier: Programming Language :: Python :: 3.12
Requires-Python: >=3.10
Requires-Dist: google-api-python-client
Requires-Dist: google-auth-httplib2
Requires-Dist: google-auth-oauthlib
Requires-Dist: mcp
Requires-Dist: python-dotenv
